{"metadata":{"dist-tags":{"latest":"0.25.10"},"versions":{"0.0.1":{"name":"@esbuild/openharmony-arm64","dist":{"tarball":"https://registry.npmjs.org/@esbuild/openharmony-arm64/-/openharmony-arm64-0.0.1.tgz"},"os":["openharmony"],"cpu":["arm64"]},"0.25.6":{"name":"@esbuild/openharmony-arm64","dist":{"tarball":"https://registry.npmjs.org/@esbuild/openharmony-arm64/-/openharmony-arm64-0.25.6.tgz"},"os":["openharmony"],"cpu":["arm64"]},"0.25.7":{"name":"@esbuild/openharmony-arm64","dist":{"tarball":"https://registry.npmjs.org/@esbuild/openharmony-arm64/-/openharmony-arm64-0.25.7.tgz"},"os":["openharmony"],"cpu":["arm64"]},"0.25.8":{"name":"@esbuild/openharmony-arm64","dist":{"tarball":"https://registry.npmjs.org/@esbuild/openharmony-arm64/-/openharmony-arm64-0.25.8.tgz"},"os":["openharmony"],"cpu":["arm64"]},"0.25.9":{"name":"@esbuild/openharmony-arm64","dist":{"tarball":"https://registry.npmjs.org/@esbuild/openharmony-arm64/-/openharmony-arm64-0.25.9.tgz"},"os":["openharmony"],"cpu":["arm64"]},"0.25.10":{"name":"@esbuild/openharmony-arm64","dist":{"tarball":"https://registry.npmjs.org/@esbuild/openharmony-arm64/-/openharmony-arm64-0.25.10.tgz"},"os":["openharmony"],"cpu":["arm64"]}},"time":{"created":"2025-07-07T00:56:30.618Z","modified":"2025-09-17T16:18:35.166Z","0.0.1":"2025-07-07T00:56:30.904Z","0.25.6":"2025-07-07T16:59:09.718Z","0.25.7":"2025-07-18T22:50:54.222Z","0.25.8":"2025-07-19T19:22:51.320Z","0.25.9":"2025-08-12T23:26:22.435Z","0.25.10":"2025-09-17T16:18:34.995Z"}},"etag":"W/\"691bb78b726ff4afad56be59c16689a0\"","lastModified":"Wed, 17 Sep 2025 16:18:36 GMT"}
